silent_killers/__init__.py
silent_killers/llm_api.py
silent_killers/metrics_definitions.py
silent_killers/cli/__init__.py
silent_killers/cli/audit.py
silent_killers-0.1.8.dist-info/licenses/LICENSE
silent_killers-0.1.8.dist-info/METADATA
silent_killers-0.1.8.dist-info/WHEEL
silent_killers-0.1.8.dist-info/entry_points.txt
silent_killers-0.1.8.dist-info/top_level.txt
silent_killers-0.1.8.dist-info/RECORD
